{
  "id": "b1802820-319b-4807-be10-227009934e38",
  "prevId": "d74a0057-7d16-424d-9b5e-1779d7c34d66",
  "version": "7",
  "dialect": "postgresql",
  "tables": {
    "public.users": {
      "name": "users",
      "schema": "",
      "columns": {
        "id": {
          "name": "id",
          "type": "integer",
          "primaryKey": true,
          "notNull": true,
          "identity": {
            "type": "always",
            "name": "users_id_seq",
            "schema": "public",
            "increment": "1",
            "startWith": "1",
            "minValue": "1",
            "maxValue": "2147483647",
            "cache": "1",
            "cycle": false
          }
        },
        "email": {
          "name": "email",
          "type": "varchar(255)",
          "primaryKey": false,
          "notNull": true
        },
        "password": {
          "name": "password",
          "type": "varchar(255)",
          "primaryKey": false,
          "notNull": true
        }
      },
      "indexes": {},
      "foreignKeys": {},
      "compositePrimaryKeys": {},
      "uniqueConstraints": {
        "users_email_unique": {
          "name": "users_email_unique",
          "nullsNotDistinct": false,
          "columns": [
            "email"
          ]
        }
      },
      "policies": {},
      "checkConstraints": {},
      "isRLSEnabled": false
    },
    "public.translations": {
      "name": "translations",
      "schema": "",
      "columns": {
        "id": {
          "name": "id",
          "type": "integer",
          "primaryKey": true,
          "notNull": true,
          "identity": {
            "type": "always",
            "name": "translations_id_seq",
            "schema": "public",
            "increment": "1",
            "startWith": "1",
            "minValue": "1",
            "maxValue": "2147483647",
            "cache": "1",
            "cycle": false
          }
        },
        "language": {
          "name": "language",
          "type": "varchar(255)",
          "primaryKey": false,
          "notNull": true
        },
        "translations": {
          "name": "translations",
          "type": "json",
          "primaryKey": false,
          "notNull": true
        }
      },
      "indexes": {},
      "foreignKeys": {},
      "compositePrimaryKeys": {},
      "uniqueConstraints": {
        "translations_language_unique": {
          "name": "translations_language_unique",
          "nullsNotDistinct": false,
          "columns": [
            "language"
          ]
        }
      },
      "policies": {},
      "checkConstraints": {},
      "isRLSEnabled": false
    },
    "public.products": {
      "name": "products",
      "schema": "",
      "columns": {
        "id": {
          "name": "id",
          "type": "integer",
          "primaryKey": true,
          "notNull": true,
          "identity": {
            "type": "always",
            "name": "products_id_seq",
            "schema": "public",
            "increment": "1",
            "startWith": "1",
            "minValue": "1",
            "maxValue": "2147483647",
            "cache": "1",
            "cycle": false
          }
        },
        "articleNo": {
          "name": "articleNo",
          "type": "varchar",
          "primaryKey": false,
          "notNull": false
        },
        "name": {
          "name": "name",
          "type": "varchar",
          "primaryKey": false,
          "notNull": false
        },
        "inPrice": {
          "name": "inPrice",
          "type": "integer",
          "primaryKey": false,
          "notNull": false
        },
        "price": {
          "name": "price",
          "type": "integer",
          "primaryKey": false,
          "notNull": false
        },
        "unit": {
          "name": "unit",
          "type": "varchar",
          "primaryKey": false,
          "notNull": false
        },
        "inStock": {
          "name": "inStock",
          "type": "integer",
          "primaryKey": false,
          "notNull": false
        },
        "description": {
          "name": "description",
          "type": "varchar",
          "primaryKey": false,
          "notNull": false
        },
        "userId": {
          "name": "userId",
          "type": "integer",
          "primaryKey": false,
          "notNull": true
        }
      },
      "indexes": {},
      "foreignKeys": {
        "products_userId_users_id_fk": {
          "name": "products_userId_users_id_fk",
          "tableFrom": "products",
          "tableTo": "users",
          "columnsFrom": [
            "userId"
          ],
          "columnsTo": [
            "id"
          ],
          "onDelete": "no action",
          "onUpdate": "no action"
        }
      },
      "compositePrimaryKeys": {},
      "uniqueConstraints": {},
      "policies": {},
      "checkConstraints": {},
      "isRLSEnabled": false
    }
  },
  "enums": {},
  "schemas": {},
  "sequences": {},
  "roles": {},
  "policies": {},
  "views": {},
  "_meta": {
    "columns": {},
    "schemas": {},
    "tables": {}
  }
}